iama/__init__.py
iama/features.py
iama/model.py
iama-0.1.4.dist-info/LICENSE.txt
iama-0.1.4.dist-info/METADATA
iama-0.1.4.dist-info/WHEEL
iama-0.1.4.dist-info/top_level.txt
iama-0.1.4.dist-info/RECORD
