Metadata-Version: 2.1
Name: iama
Version: 0.1.4
Summary: Classifying r/relationships post titles by gender.
Home-page: https://github.com/youdaniel/iama
Author: Daniel You
Author-email: daniel.you@jerichoapps.org
License: Apache 2.0
Platform: UNKNOWN
Classifier: Development Status :: 3 - Alpha
Classifier: License :: OSI Approved :: Apache Software License
Classifier: Operating System :: OS Independent
Classifier: Programming Language :: Python :: 3
Classifier: Programming Language :: Python :: 3 :: Only
Requires-Python: >=3.6
License-File: LICENSE.txt
Requires-Dist: nltk
Requires-Dist: setuptools
Requires-Dist: scikit-learn
Requires-Dist: numpy
